setup.py
src/zc/__init__.py
src/zc.authorizedotnet.egg-info/PKG-INFO
src/zc.authorizedotnet.egg-info/SOURCES.txt
src/zc.authorizedotnet.egg-info/dependency_links.txt
src/zc.authorizedotnet.egg-info/namespace_packages.txt
src/zc.authorizedotnet.egg-info/requires.txt
src/zc.authorizedotnet.egg-info/top_level.txt
src/zc/authorizedotnet/README.txt
src/zc/authorizedotnet/__init__.py
src/zc/authorizedotnet/processing.py
src/zc/authorizedotnet/tests.py