Metadata-Version: 1.0
Name: zc.authorizedotnet
Version: 1.3.1
Summary: A simple interface to Authorize.Net's AIM API
Home-page: http://svn.zope.org/zc.authorizedotnet
Author: Zope Corporation
Author-email: zope-dev@zope.org
License: ZPL 2.1
Keywords: credit card authorize.net CC AIM
Platform: UNKNOWN
Classifier: Intended Audience :: Developers
Classifier: License :: OSI Approved :: Zope Public License
Classifier: Topic :: Software Development :: Libraries :: Python Modules
